mkbak_iterfzf/__init__.py
mkbak_iterfzf/py.typed
mkbak_iterfzf-0.7.0.25.1.dist-info/LICENSE
mkbak_iterfzf-0.7.0.25.1.dist-info/METADATA
mkbak_iterfzf-0.7.0.25.1.dist-info/WHEEL
mkbak_iterfzf-0.7.0.25.1.dist-info/top_level.txt
mkbak_iterfzf-0.7.0.25.1.dist-info/RECORD
